universal_mcp_whatsapp/README.md
universal_mcp_whatsapp/__init__.py
universal_mcp_whatsapp/app.py
universal_mcp_whatsapp/audio.py
universal_mcp_whatsapp/server.py
universal_mcp_whatsapp/whatsapp.py
universal_mcp_whatsapp-0.1.3.dist-info/METADATA
universal_mcp_whatsapp-0.1.3.dist-info/WHEEL
universal_mcp_whatsapp-0.1.3.dist-info/entry_points.txt
universal_mcp_whatsapp-0.1.3.dist-info/licenses/LICENSE
universal_mcp_whatsapp-0.1.3.dist-info/RECORD
