Metadata-Version: 2.4
Name: universal-mcp-whatsapp
Version: 0.1.3
Summary: A Universal MCP Application: universal_mcp_whatsapp
Project-URL: Homepage, https://github.com/universal-mcp/whatsapp
Project-URL: Repository, https://github.com/universal-mcp/whatsapp
Author-email: Manoj Bajaj <manoj@agentr.dev>
License: MIT
License-File: LICENSE
Classifier: License :: OSI Approved :: MIT License
Classifier: Operating System :: OS Independent
Classifier: Programming Language :: Python :: 3
Classifier: Programming Language :: Python :: 3.11
Requires-Python: >=3.11
Requires-Dist: langgraph>=0.6.4
Requires-Dist: pytest>=8.4.1
Requires-Dist: python-dotenv>=1.0.0
Requires-Dist: universal-mcp==0.1.23
Provides-Extra: dev
Requires-Dist: pre-commit; extra == 'dev'
Requires-Dist: ruff; extra == 'dev'
Provides-Extra: test
Requires-Dist: pytest-cov; extra == 'test'
Requires-Dist: pytest<9.0.0,>=7.0.0; extra == 'test'
